personrole/__init__.py
personrole-0.1.dist-info/LICENCE.txt
personrole-0.1.dist-info/METADATA
personrole-0.1.dist-info/WHEEL
personrole-0.1.dist-info/top_level.txt
personrole-0.1.dist-info/RECORD
