Metadata-Version: 2.2
Name: personrole
Version: 0.1
Summary: using this package can findout of the person role as student or employee or pensinor based on age
Author: K Saral Kumar
Author-email: saralkumar28@gmail.com
Classifier: Programming Language :: Python :: 3
Classifier: License :: OSI Approved :: MIT License
Classifier: Operating System :: OS Independent
License-File: LICENCE.txt
Dynamic: author
Dynamic: author-email
Dynamic: classifier
Dynamic: summary
